mermaid/__init__.py
mermaid/mermaid.py
mermaid_python-0.1.dist-info/LICENSE
mermaid_python-0.1.dist-info/METADATA
mermaid_python-0.1.dist-info/WHEEL
mermaid_python-0.1.dist-info/top_level.txt
mermaid_python-0.1.dist-info/RECORD
