Metadata-Version: 2.1
Name: mermaid-python
Version: 0.1
Summary: A package for generating diagrams using Mermaid JS
Classifier: Programming Language :: Python :: 3
Classifier: License :: OSI Approved :: MIT License
Classifier: Operating System :: OS Independent
Requires-Python: >=3.7
License-File: LICENSE
